dc/__init__.py
dc/dowker_complex.py
dowker_complex-1.0.0.dist-info/licenses/LICENSE
dowker_complex-1.0.0.dist-info/METADATA
dowker_complex-1.0.0.dist-info/WHEEL
dowker_complex-1.0.0.dist-info/top_level.txt
dowker_complex-1.0.0.dist-info/RECORD
