Metadata-Version: 2.4
Name: dowker-complex
Version: 1.0.0
Summary: Implementation of the Dowker complex.
Author: m-a-huber
License-Expression: MIT
Project-URL: Homepage, https://github.com/m-a-huber/dowker-complex
Project-URL: Issues, https://github.com/m-a-huber/dowker-complex/issues
Requires-Python: >=3.10
License-File: LICENSE
Requires-Dist: gudhi>=3.11.0
Requires-Dist: numba>=0.61.2
Requires-Dist: numpy>=2.2.6
Requires-Dist: scikit-learn>=1.7.1
Requires-Dist: typing-extensions>=4.14.1
Dynamic: license-file
